napari_spatial_correlation_plotter/__init__.py
napari_spatial_correlation_plotter/_nice_colormap.py
napari_spatial_correlation_plotter/_widget.py
napari_spatial_correlation_plotter/napari.yaml
napari_spatial_correlation_plotter/_tests/__init__.py
napari_spatial_correlation_plotter-0.0.3.dist-info/LICENSE
napari_spatial_correlation_plotter-0.0.3.dist-info/METADATA
napari_spatial_correlation_plotter-0.0.3.dist-info/WHEEL
napari_spatial_correlation_plotter-0.0.3.dist-info/entry_points.txt
napari_spatial_correlation_plotter-0.0.3.dist-info/top_level.txt
napari_spatial_correlation_plotter-0.0.3.dist-info/RECORD
