Metadata-Version: 2.1
Name: napari-spatial-correlation-plotter
Version: 0.0.3
Summary: A plugin to compute and display spatial correlation histograms in Napari
Home-page: https://github.com/jules-vanaret/napari-spatial-correlation-plotter
Author: Jules Vanaret
Author-email: jules.vanaret@univ-amu.fr
License: MIT
Project-URL: Bug Tracker, https://github.com/jules-vanaret/napari-spatial-correlation-plotter/issues
Project-URL: Documentation, https://github.com/jules-vanaret/napari-spatial-correlation-plotter#README.md
Project-URL: Source Code, https://github.com/jules-vanaret/napari-spatial-correlation-plotter
Project-URL: User Support, https://github.com/jules-vanaret/napari-spatial-correlation-plotter/issues
Classifier: Development Status :: 2 - Pre-Alpha
Classifier: Framework :: napari
Classifier: Intended Audience :: Developers
Classifier: License :: OSI Approved :: MIT License
Classifier: Operating System :: OS Independent
Classifier: Programming Language :: Python
Classifier: Programming Language :: Python :: 3
Classifier: Programming Language :: Python :: 3 :: Only
Classifier: Programming Language :: Python :: 3.8
Classifier: Programming Language :: Python :: 3.9
Classifier: Programming Language :: Python :: 3.10
Classifier: Topic :: Scientific/Engineering :: Image Processing
Requires-Python: >=3.8
License-File: LICENSE
Requires-Dist: numpy
Requires-Dist: magicgui
Requires-Dist: matplotlib
Requires-Dist: scikit-image
Requires-Dist: qtpy
Requires-Dist: pyclesperanto-prototype
Requires-Dist: tapenade
Provides-Extra: testing
Requires-Dist: tox; extra == "testing"
Requires-Dist: pytest; extra == "testing"
Requires-Dist: pytest-cov; extra == "testing"
Requires-Dist: pytest-qt; extra == "testing"
Requires-Dist: napari; extra == "testing"
Requires-Dist: pyqt5; extra == "testing"
